ucloudstorage/__init__.py
ucloudstorage/base.py
ucloudstorage/drivers/__init__.py
ucloudstorage/drivers/amazon/__init__.py
ucloudstorage/drivers/amazon/exceptions.py
ucloudstorage/drivers/amazon/s3.py
ucloudstorage-0.1.3.dist-info/LICENSE
ucloudstorage-0.1.3.dist-info/WHEEL
ucloudstorage-0.1.3.dist-info/METADATA
ucloudstorage-0.1.3.dist-info/RECORD
