Metadata-Version: 2.1
Name: ucloudstorage
Version: 0.1.3
Summary: 
Author: Breno Moura
Author-email: breno.mm@outlook.com
Requires-Python: >=3.8,<4.0
Classifier: Programming Language :: Python :: 3
Classifier: Programming Language :: Python :: 3.8
Classifier: Programming Language :: Python :: 3.9
Classifier: Programming Language :: Python :: 3.10
Classifier: Programming Language :: Python :: 3.11
Requires-Dist: aiobotocore (>=2.4.2,<3.0.0)
Requires-Dist: pytest (>=7.2.1,<8.0.0)
Requires-Dist: pytest-asyncio (>=0.20.3,<0.21.0)
Requires-Dist: typing-extensions (>=4.4.0,<5.0.0)
